{
  "outDir": "src/typegenTypes",
  "specVersions": "https://v2.archive.subsquid.io/metadata/hydradx",
  "pallets": {
    "AssetRegistry": {
      "events": ["Registered", "Updated"],
      "storage": ["Assets"]
    },
    "Balances": {
      "events": ["Transfer"],
      "calls": [],
      "storage": [],
      "constants": []
    },
    "Tokens": {
      "events": ["Transfer"],
      "storage": ["Accounts"]
    },
    "ParachainSystem": {
      "calls": ["set_validation_data"],
      "storage": ["LastRelayChainBlockNumber"]
    },
    "XYK": {
      "events": ["PoolCreated", "PoolDestroyed", "SellExecuted", "BuyExecuted"],
      "calls": ["create_pool"],
      "storage": ["PoolAssets"]
    },
    "Omnipool": {
      "events": ["TokenAdded", "TokenRemoved", "SellExecuted", "BuyExecuted"],
      "calls": [],
      "storage": ["Assets"]
    },
    "Stableswap": {
      "events": [
        "PoolCreated",
        "SellExecuted",
        "BuyExecuted",
        "LiquidityAdded",
        "LiquidityRemoved"
      ],
      "storage": ["Pools"]
    },
    "LBP": {
      "events": ["PoolUpdated", "PoolCreated", "SellExecuted", "BuyExecuted"],
      "calls": ["create_pool"]
    },
    "System": {
      "storage": ["Account"]
    }
  }
}
